newtex/__init__.py
newtex/_git.py
newtex/_version.py
newtex/util.py
newtex/newtexrc/fabfile.py
newtex/newtexrc/gitignore
newtex/newtexrc/template.tex
newtex/newtexrc/bib/.keep
newtex/newtexrc/bst/achemso-small.bst
newtex/newtexrc/bst/achemso-titles-url-thesis.bst
newtex/newtexrc/bst/achemso.bst
newtex/newtexrc/bst/acs-bibtex-nomonth-url.bst
newtex/newtexrc/bst/acs-bibtex-nomonth.bst
newtex/newtexrc/bst/apsrev_marohn.bst
newtex/newtexrc/bst/apsrev_marohn_apl.bst
newtex/newtexrc/bst/apsrev_nonote.bst
newtex/newtexrc/bst/naturemag.bst
newtex/newtexrc/bst/naturemag_jm.bst
newtex/newtexrc/bst/naturemag_jm_jro.bst
newtex/newtexrc/bst/naturemag_nourl.bst
newtex/newtexrc/bst/naturemag_nourl_tiny.bst
newtex/newtexrc/bst/pccp-bibtex-nomonth-title-url-conf-note.bst
newtex/newtexrc/bst/pccp-bibtex-nomonth-title-url-conf.bst
newtex/newtexrc/bst/pccp-bibtex-nomonth-url.bst
newtex/newtexrc/bst/pccp-bibtex-nomonth.bst
newtex/newtexrc/bst/pccp-bibtex.bst
newtex/newtexrc/correspondence/.keep
newtex/newtexrc/figs/ex.pdf
newtex/newtexrc/scripts/.keep
newtex/newtexrc/submit/.keep
newtex/tests/test_git.py
newtex-0.3.8.dist-info/DESCRIPTION.rst
newtex-0.3.8.dist-info/METADATA
newtex-0.3.8.dist-info/RECORD
newtex-0.3.8.dist-info/WHEEL
newtex-0.3.8.dist-info/entry_points.txt
newtex-0.3.8.dist-info/metadata.json
newtex-0.3.8.dist-info/top_level.txt
