Metadata-Version: 2.0
Name: newtex
Version: 0.3.8
Summary: Create a new LaTeX document.
Home-page: https://github.com/ryanpdwyer/newtex
Author: Ryan Dwyer
Author-email: ryanpdwyer@gmail.com
License: MIT
Platform: UNKNOWN
Classifier: Development Status :: 3 - Alpha
Classifier: Intended Audience :: Science/Research
Classifier: License :: OSI Approved :: MIT License
Classifier: Operating System :: MacOS :: MacOS X
Classifier: Operating System :: Microsoft :: Windows
Classifier: Operating System :: POSIX
Classifier: Programming Language :: Python :: 2
Classifier: Programming Language :: Python :: 2.7
Requires-Dist: PyYAML
Requires-Dist: click
Requires-Dist: pathlib
